README.rst
setup.py
bin/sixgill_build
bin/sixgill_filter
bin/sixgill_makefasta
bin/sixgill_merge
sixgill/__init__.py
sixgill/dna.py
sixgill/metapeptides.py
sixgill/version.py
sixgill.egg-info/PKG-INFO
sixgill.egg-info/SOURCES.txt
sixgill.egg-info/dependency_links.txt
sixgill.egg-info/requires.txt
sixgill.egg-info/top_level.txt