Metadata-Version: 1.1
Name: sixgill
Version: 0.2.4
Summary: six-frame genome-inferred libraries for LC-MS/MS
Home-page: UNKNOWN
Author: Damon May
Author-email: damonmay@uw.edu
License: Apache
Keywords: proteomics metaproteomics metagenomics
Platform: UNKNOWN
Classifier: Development Status :: 4 - Beta
Classifier: Topic :: Scientific/Engineering :: Bio-Informatics
Classifier: Intended Audience :: Science/Research
Classifier: License :: OSI Approved :: Apache Software License
Classifier: Programming Language :: Python :: 2
Classifier: Programming Language :: Python :: 2.7
